src/main.py
src/utils.py
yaml2terragrunt-0.1.1.dist-info/LICENSE
yaml2terragrunt-0.1.1.dist-info/LICENSE-CODE
yaml2terragrunt-0.1.1.dist-info/METADATA
yaml2terragrunt-0.1.1.dist-info/WHEEL
yaml2terragrunt-0.1.1.dist-info/RECORD
