Metadata-Version: 2.1
Name: yaml2terragrunt
Version: 0.1.1
Summary: yaml2terragrunt is an open-source project designed to enable the dynamic creation of Terragrunt files, folders, and configurations using a declarative YAML approach. The primary objective is to simplify and streamline the management of complex infrastructure-as-code setups, particularly for organizations dealing with multiple environments, regions, and services.
License: GPL-3.0
Author: Leonard Avevor
Author-email: deamcoder@gmail.com
Requires-Python: >=3.8,<4.0
Classifier: License :: OSI Approved :: GNU General Public License v3 (GPLv3)
Classifier: Programming Language :: Python :: 3
Classifier: Programming Language :: Python :: 3.8
Classifier: Programming Language :: Python :: 3.9
Classifier: Programming Language :: Python :: 3.10
Classifier: Programming Language :: Python :: 3.11
Classifier: Programming Language :: Python :: 3.12
Requires-Dist: PyYAML (>=6.0.2,<7.0.0)
